botcreator/__init__.py
botcreator/botcreator.py
botcreator-0.1.1.dist-info/METADATA
botcreator-0.1.1.dist-info/WHEEL
botcreator-0.1.1.dist-info/top_level.txt
botcreator-0.1.1.dist-info/RECORD
