Metadata-Version: 2.1
Name: botcreator
Version: 0.1.1
Summary: Easy chatbot development with Python. Create your own chatbots with just a few lines of code.
Author: EdexCode
Author-email: edexcode@gmail.com
License: MIT License
Project-URL: GitHub, https://github.com/EdexCode/BotCreator
Keywords: python,bot,chatbot,botdeveloper,predefined
Classifier: License :: OSI Approved :: MIT License
Classifier: Development Status :: 2 - Pre-Alpha
Classifier: Intended Audience :: Developers
Classifier: Programming Language :: Python :: 3
Classifier: Operating System :: OS Independent
